{
  "D:\\Jonathan\\downloads\\pydp\\pydp\\src": {
    "files": {
      "pack.mcmeta": "1ade5bbc9587445b91bdd65d0ad312ec",
      "data\\a\\functions\\check_for_empty_slots.mcfunction": "c4a278f88e5aa20979c01dbb78fdd831",
      "data\\a\\functions\\check_for_empty_slots\\else.mcfunction": "ece045e7d2a53d7d40bd8931a9251fd9",
      "data\\a\\functions\\check_for_empty_slots\\else_2.mcfunction": "8dccaec3b2dd592d3b23e0eae95a689f",
      "data\\a\\functions\\check_for_empty_slots\\else_3.mcfunction": "dc37581e7fa4d163af090f1afa78fc3d",
      "data\\a\\functions\\check_for_empty_slots\\else_4.mcfunction": "11e4490d66f4c8bcd0e99f75b51c893c",
      "data\\a\\functions\\check_for_empty_slots\\else_5.mcfunction": "b1366a2a106a6c4751327ec490c6759c",
      "data\\a\\functions\\check_for_empty_slots\\else_6.mcfunction": "b594abe97d1e85fc87260335e2dc90ce",
      "data\\a\\functions\\check_for_empty_slots\\else_7.mcfunction": "d6f2407786788bd31187630c42af9a21",
      "data\\a\\functions\\check_for_empty_slots\\else_8.mcfunction": "a4e6472a64650d2d6fa763110dc39e7d",
      "data\\a\\functions\\check_for_empty_slots\\else_9.mcfunction": "c595566bf10e6f11fdc0535732330793",
      "data\\a\\functions\\check_for_empty_slots\\else_10.mcfunction": "c6bba287c3b9f8f111f4a982c7282919",
      "data\\a\\functions\\check_for_empty_slots\\else_11.mcfunction": "b451fd486fdc3105fad01703f3f9ce50",
      "data\\a\\functions\\check_for_empty_slots\\else_12.mcfunction": "a7443e65fbb7aac525979f9b62c0a5a0",
      "data\\a\\functions\\check_for_empty_slots\\else_13.mcfunction": "c3bd3a7aabc8f37afab6293b07e9ae30",
      "data\\a\\functions\\check_for_empty_slots\\else_14.mcfunction": "8a273959a6877f25e7a264a7f567c696",
      "data\\a\\functions\\check_for_empty_slots\\else_15.mcfunction": "05f5d464130ec51d99b732b5e210d454",
      "data\\a\\functions\\check_for_empty_slots\\else_16.mcfunction": "c1609f5436c193ae1b78f3c84405e37f",
      "data\\a\\functions\\check_for_empty_slots\\else_17.mcfunction": "34c5d45ee9c2e60a290a326b36048bc1",
      "data\\a\\functions\\check_for_empty_slots\\else_18.mcfunction": "dfefeafffad979b9d251f468ec07931b",
      "data\\a\\functions\\check_for_empty_slots\\else_19.mcfunction": "7959d1e5da74a7e872a3fac8705a6369",
      "data\\a\\functions\\check_for_empty_slots\\else_20.mcfunction": "35470a203c8adb9366885cfc3e99db35",
      "data\\a\\functions\\check_for_empty_slots\\else_21.mcfunction": "ac1919a7aeb27f0b71c2438fb6223755",
      "data\\a\\functions\\check_for_empty_slots\\else_22.mcfunction": "fbfbd363ab5c1222bf1db81ba73064e7",
      "data\\a\\functions\\check_for_empty_slots\\else_23.mcfunction": "930b07c1c86a6e3a2a5cdf55bbf1a31e",
      "data\\a\\functions\\check_for_empty_slots\\else_24.mcfunction": "81fd8c98318b43cf0426fec75e2d74a5",
      "data\\a\\functions\\check_for_empty_slots\\else_25.mcfunction": "f15ef802010c2d638c7c355d8e0c37ca",
      "data\\a\\functions\\check_for_empty_slots\\else_26.mcfunction": "ba424eeaf8c174140901e265be6eac47",
      "data\\a\\functions\\check_for_empty_slots\\else_27.mcfunction": "901abd4f3724e3ecf928380f21e40e52",
      "data\\a\\functions\\check_for_empty_slots\\else_28.mcfunction": "b06719f2acd35630760c866be1e5cd0e",
      "data\\a\\functions\\check_for_empty_slots\\else_29.mcfunction": "ff799322b02f0bb12531878334d19b44",
      "data\\a\\functions\\check_for_empty_slots\\else_30.mcfunction": "035b77aed7bd31d1a0c1925b608ba43b",
      "data\\a\\functions\\check_for_empty_slots\\else_31.mcfunction": "5bb5daaa0abe966d0e739836ed9eac64",
      "data\\a\\functions\\check_for_empty_slots\\else_32.mcfunction": "fbdb6cbd3933046324810328b887dec0",
      "data\\a\\functions\\check_for_empty_slots\\else_33.mcfunction": "ddea79145c9b7be7066ec98a35cb9096",
      "data\\a\\functions\\check_for_empty_slots\\else_34.mcfunction": "79f0bdc411ae97b2340ad601c1378bbc",
      "data\\a\\functions\\check_for_empty_slots\\else_35.mcfunction": "4b437392ea972752e2b720a82591a33a",
      "data\\a\\functions\\check_for_empty_slots\\else_36.mcfunction": "802b2784df503a6a973e8f04beb8f8a1",
      "data\\a\\functions\\load.mcfunction": "f02018bbe8bc6f54817c00b959dd0cf8",
      "data\\a\\functions\\__init__.mcfunction": "e13c960c8072f2b0d5b06799b2f0757e",
      "data\\minecraft\\tags\\functions\\load.json": "a372f10b1bc21f2cd6b3fda9e92293a2"
    },
    "resultFolder": "C:\\Users\\Jonathan\\AppData\\Roaming\\.minecraft\\saves\\datapack test world\\datapacks\\pydp"
  }
}